play_and_code/__init__.py
play_and_code-0.0.2.dist-info/METADATA
play_and_code-0.0.2.dist-info/WHEEL
play_and_code-0.0.2.dist-info/top_level.txt
play_and_code-0.0.2.dist-info/RECORD
